google/cloud/parallelstore/__init__.py
google/cloud/parallelstore/gapic_version.py
google/cloud/parallelstore/py.typed
google/cloud/parallelstore_v1/__init__.py
google/cloud/parallelstore_v1/gapic_metadata.json
google/cloud/parallelstore_v1/gapic_version.py
google/cloud/parallelstore_v1/py.typed
google/cloud/parallelstore_v1/services/__init__.py
google/cloud/parallelstore_v1/services/parallelstore/__init__.py
google/cloud/parallelstore_v1/services/parallelstore/async_client.py
google/cloud/parallelstore_v1/services/parallelstore/client.py
google/cloud/parallelstore_v1/services/parallelstore/pagers.py
google/cloud/parallelstore_v1/services/parallelstore/transports/__init__.py
google/cloud/parallelstore_v1/services/parallelstore/transports/base.py
google/cloud/parallelstore_v1/services/parallelstore/transports/grpc.py
google/cloud/parallelstore_v1/services/parallelstore/transports/grpc_asyncio.py
google/cloud/parallelstore_v1/services/parallelstore/transports/rest.py
google/cloud/parallelstore_v1/services/parallelstore/transports/rest_base.py
google/cloud/parallelstore_v1/types/__init__.py
google/cloud/parallelstore_v1/types/parallelstore.py
google/cloud/parallelstore_v1beta/__init__.py
google/cloud/parallelstore_v1beta/gapic_metadata.json
google/cloud/parallelstore_v1beta/gapic_version.py
google/cloud/parallelstore_v1beta/py.typed
google/cloud/parallelstore_v1beta/services/__init__.py
google/cloud/parallelstore_v1beta/services/parallelstore/__init__.py
google/cloud/parallelstore_v1beta/services/parallelstore/async_client.py
google/cloud/parallelstore_v1beta/services/parallelstore/client.py
google/cloud/parallelstore_v1beta/services/parallelstore/pagers.py
google/cloud/parallelstore_v1beta/services/parallelstore/transports/__init__.py
google/cloud/parallelstore_v1beta/services/parallelstore/transports/base.py
google/cloud/parallelstore_v1beta/services/parallelstore/transports/grpc.py
google/cloud/parallelstore_v1beta/services/parallelstore/transports/grpc_asyncio.py
google_cloud_parallelstore-0.5.0.dist-info/licenses/LICENSE
google_cloud_parallelstore-0.5.0.dist-info/METADATA
google_cloud_parallelstore-0.5.0.dist-info/WHEEL
google_cloud_parallelstore-0.5.0.dist-info/top_level.txt
google_cloud_parallelstore-0.5.0.dist-info/RECORD
